jnpython/__init__.py
jnpython/big_decimal.py
jnpython/combinatorics.py
jnpython/fraction.py
jnpython/graphs.py
jnpython/int_helper.py
jnpython/list_helper.py
jnpython/misc.py
jnpython/sorting.py
jnpython/string_helper.py
jnpython/structs.py
jnpython-0.1.6.dist-info/METADATA
jnpython-0.1.6.dist-info/WHEEL
jnpython-0.1.6.dist-info/licenses/LICENSE
jnpython-0.1.6.dist-info/RECORD
