Metadata-Version: 2.1
Name: jnpython
Version: 0.1.6
Summary: Misc python helper functions
Project-URL: Homepage, https://github.com/jnsoft/jnpython
Project-URL: Bug Tracker, https://github.com/jnsoft/jnpython/issues
Author: Johan Nilsson
License-File: LICENSE
Keywords: helpers,misc,util
Classifier: License :: OSI Approved :: MIT License
Classifier: Operating System :: OS Independent
Classifier: Programming Language :: Python :: 3
Requires-Python: >=3.8
